quasielasticbayes/Four.cp310-win_amd64.pyd
quasielasticbayes/QLdata.cp310-win_amd64.pyd
quasielasticbayes/QLres.cp310-win_amd64.pyd
quasielasticbayes/QLse.cp310-win_amd64.pyd
quasielasticbayes/Quest.cp310-win_amd64.pyd
quasielasticbayes/ResNorm.cp310-win_amd64.pyd
quasielasticbayes/__init__.py
quasielasticbayes/testing.py
quasielasticbayes-0.2.2.dist-info/LICENSE.txt
quasielasticbayes-0.2.2.dist-info/METADATA
quasielasticbayes-0.2.2.dist-info/WHEEL
quasielasticbayes-0.2.2.dist-info/top_level.txt
quasielasticbayes-0.2.2.dist-info/RECORD
