Metadata-Version: 2.1
Name: quasielasticbayes
Version: 0.2.2
Summary: A Bayesian fitting package used for fitting quasi-elastic neutron scattering (QENS) data.
Home-page: https://github.com/mantidproject/quasielasticbayes
Author: Dr. Devinder Sivia, Dr. Spencer Howells, Mantid Team
Author-email: mantid-help@mantidproject.org
License: BSD
License-File: LICENSE.txt
